nhc_image_retrieval/__init__.py
nhc_image_retrieval/lib/__init__.py
nhc_image_retrieval/lib/rss_entry.py
nhc_image_retrieval-0.0.2.dist-info/LICENSE
nhc_image_retrieval-0.0.2.dist-info/METADATA
nhc_image_retrieval-0.0.2.dist-info/WHEEL
nhc_image_retrieval-0.0.2.dist-info/top_level.txt
nhc_image_retrieval-0.0.2.dist-info/RECORD
