Metadata-Version: 2.1
Name: nhc-image-retrieval
Version: 0.0.2
Summary: Downloads images from the NOAA NHC website.
Author-email: John Barton <john@mediayoucanfeel.com>
License: The MIT License (MIT)
Project-URL: Homepage, https://github.com/JohnBarton27/nhc_image_retrieval
Keywords: hurricane,nhc,image
Classifier: License :: OSI Approved :: MIT License
Classifier: Programming Language :: Python
Classifier: Programming Language :: Python :: 3
Requires-Python: >=3.9
License-File: LICENSE
Requires-Dist: bs4
Requires-Dist: feedparser
Requires-Dist: pytz
Requires-Dist: requests
Provides-Extra: dev
Requires-Dist: black; extra == "dev"
Requires-Dist: isort; extra == "dev"
Requires-Dist: pip-tools; extra == "dev"
Requires-Dist: pytest; extra == "dev"
